simpleOption.py
simpleOption-0.2.4.dist-info/LICENSE
simpleOption-0.2.4.dist-info/METADATA
simpleOption-0.2.4.dist-info/WHEEL
simpleOption-0.2.4.dist-info/top_level.txt
simpleOption-0.2.4.dist-info/RECORD
